setuptools_scm_git_archive/__init__.py
setuptools_scm_git_archive-1.3.dist-info/LICENSE
setuptools_scm_git_archive-1.3.dist-info/METADATA
setuptools_scm_git_archive-1.3.dist-info/WHEEL
setuptools_scm_git_archive-1.3.dist-info/entry_points.txt
setuptools_scm_git_archive-1.3.dist-info/top_level.txt
setuptools_scm_git_archive-1.3.dist-info/RECORD
