Metadata-Version: 2.1
Name: setuptools_scm_git_archive
Version: 1.3
Summary: setuptools_scm plugin for git archives
Home-page: https://github.com/Changaco/setuptools_scm_git_archive/
Author: Changaco
Author-email: changaco@changaco.oy.lc
License: MIT
Keywords: scm vcs version tags git archive
Platform: UNKNOWN
License-File: LICENSE
